README.md
setup.py
src/currencycloud/__init__.py
src/currencycloud/client.py
src/currencycloud/config.py
src/currencycloud/http.py
src/currencycloud/version.py
src/currencycloud/clients/__init__.py
src/currencycloud/clients/accounts.py
src/currencycloud/clients/auth.py
src/currencycloud/clients/balances.py
src/currencycloud/clients/beneficiaries.py
src/currencycloud/clients/contacts.py
src/currencycloud/clients/conversions.py
src/currencycloud/clients/funding.py
src/currencycloud/clients/ibans.py
src/currencycloud/clients/payers.py
src/currencycloud/clients/payments.py
src/currencycloud/clients/rates.py
src/currencycloud/clients/reference.py
src/currencycloud/clients/reports.py
src/currencycloud/clients/senders.py
src/currencycloud/clients/settlements.py
src/currencycloud/clients/transactions.py
src/currencycloud/clients/transfers.py
src/currencycloud/clients/vans.py
src/currencycloud/errors/__init__.py
src/currencycloud/errors/api.py
src/currencycloud/resources/__init__.py
src/currencycloud/resources/account.py
src/currencycloud/resources/balance.py
src/currencycloud/resources/beneficiary.py
src/currencycloud/resources/contact.py
src/currencycloud/resources/conversion.py
src/currencycloud/resources/funding.py
src/currencycloud/resources/iban.py
src/currencycloud/resources/paginated_collection.py
src/currencycloud/resources/pagination.py
src/currencycloud/resources/payer.py
src/currencycloud/resources/payment.py
src/currencycloud/resources/rate.py
src/currencycloud/resources/reference.py
src/currencycloud/resources/report.py
src/currencycloud/resources/resource.py
src/currencycloud/resources/sender.py
src/currencycloud/resources/settlement.py
src/currencycloud/resources/transaction.py
src/currencycloud/resources/transfer.py
src/currencycloud/resources/van.py
src/currencycloud/resources/actions/__init__.py
src/currencycloud/resources/actions/delete.py
src/currencycloud/resources/actions/update.py
src/currencycloud_python_client.egg-info/PKG-INFO
src/currencycloud_python_client.egg-info/SOURCES.txt
src/currencycloud_python_client.egg-info/dependency_links.txt
src/currencycloud_python_client.egg-info/requires.txt
src/currencycloud_python_client.egg-info/top_level.txt